<?xml version="1.0" encoding="utf-8"?>
<SoundBanksInfo Platform="Windows" BasePlatform="Windows" SchemaVersion="11" SoundbankVersion="128">
	<RootPaths>
		<ProjectRoot>F:\TranceMission\PinkTransmission\WwiseProject\TranceMissionFGJ\</ProjectRoot>
		<SourceFilesRoot>F:\TranceMission\PinkTransmission\WwiseProject\TranceMissionFGJ\.cache\Windows\</SourceFilesRoot>
		<SoundBanksRoot>F:\TranceMission\PinkTransmission\WwiseProject\TranceMissionFGJ\GeneratedSoundBanks\Windows\</SoundBanksRoot>
		<ExternalSourcesInputFile></ExternalSourcesInputFile>
		<ExternalSourcesOutputRoot>F:\TranceMission\PinkTransmission\WwiseProject\TranceMissionFGJ\GeneratedSoundBanks\Windows\</ExternalSourcesOutputRoot>
	</RootPaths>
	<DialogueEvents/>
	<StreamedFiles/>
	<MediaFilesNotInAnyBank/>
	<SoundBanks>
		<SoundBank Id="1355168291" Language="SFX">
			<ObjectPath>Init</ObjectPath>
			<ShortName>Init</ShortName>
			<Path>Init.bnk</Path>
		</SoundBank>
		<SoundBank Id="2469504869" Language="SFX">
			<ObjectPath>\SoundBanks\Default Work Unit\Master_SoundBank</ObjectPath>
			<ShortName>Master_SoundBank</ShortName>
			<Path>Master_SoundBank.bnk</Path>
			<IncludedEvents>
				<Event Id="1492365381" Name="ActionBiteStinger" ObjectPath="\Events\Default Work Unit\Actions\ActionBiteStinger"/>
				<Event Id="854939776" Name="ActionFirstMove" ObjectPath="\Events\Default Work Unit\Actions\ActionFirstMove" MaxAttenuation="0,000000"/>
				<Event Id="4202577283" Name="ActionShroomStinger" ObjectPath="\Events\Default Work Unit\Actions\ActionShroomStinger"/>
				<Event Id="1313304943" Name="Marker" ObjectPath="\Events\Default Work Unit\Markers\Marker" MaxAttenuation="0,000000"/>
				<Event Id="2526194360" Name="PercussionStinger" ObjectPath="\Events\Default Work Unit\Actions\PercussionStinger" MaxAttenuation="0,000000"/>
				<Event Id="1229115632" Name="PlayPlaceholderLoop" ObjectPath="\Events\Default Work Unit\Music\PlayPlaceholderLoop"/>
				<Event Id="3076088854" Name="StopPlaceholderLoop" ObjectPath="\Events\Default Work Unit\Music\StopPlaceholderLoop" MaxAttenuation="0,000000"/>
			</IncludedEvents>
			<IncludedMemoryFiles>
				<File Id="4336932" Language="SFX">
					<ShortName>Stinger3.wav</ShortName>
					<Path>SFX\Stinger3_F17FB28C.wem</Path>
				</File>
				<File Id="10769914" Language="SFX">
					<ShortName>Splat3.wav</ShortName>
					<Path>SFX\Splat3_01C072E3.wem</Path>
				</File>
				<File Id="15291811" Language="SFX">
					<ShortName>StingerPerc3.wav</ShortName>
					<Path>SFX\StingerPerc3_F17FB28C.wem</Path>
				</File>
				<File Id="249197451" Language="SFX">
					<ShortName>StingerPerc4.wav</ShortName>
					<Path>SFX\StingerPerc4_F17FB28C.wem</Path>
				</File>
				<File Id="281406132" Language="SFX">
					<ShortName>Splat_base.wav</ShortName>
					<Path>SFX\Splat_base_2CA90D9E.wem</Path>
				</File>
				<File Id="284848740" Language="SFX">
					<ShortName>StingerPerc6.wav</ShortName>
					<Path>SFX\StingerPerc6_F17FB28C.wem</Path>
				</File>
				<File Id="359132591" Language="SFX">
					<ShortName>Crash.wav</ShortName>
					<Path>SFX\Crash_F17FB28C.wem</Path>
				</File>
				<File Id="362299644" Language="SFX">
					<ShortName>StingerBite4.wav</ShortName>
					<Path>SFX\StingerBite4_F17FB28C.wem</Path>
				</File>
				<File Id="393984883" Language="SFX">
					<ShortName>StingerBite2.wav</ShortName>
					<Path>SFX\StingerBite2_F17FB28C.wem</Path>
				</File>
				<File Id="455516844" Language="SFX">
					<ShortName>StingerBite1.wav</ShortName>
					<Path>SFX\StingerBite1_F17FB28C.wem</Path>
				</File>
				<File Id="506096902" Language="SFX">
					<ShortName>Stinger1.wav</ShortName>
					<Path>SFX\Stinger1_F17FB28C.wem</Path>
				</File>
				<File Id="513632677" Language="SFX">
					<ShortName>StingerPerc5.wav</ShortName>
					<Path>SFX\StingerPerc5_F17FB28C.wem</Path>
				</File>
				<File Id="532581590" Language="SFX">
					<ShortName>Stinger2.wav</ShortName>
					<Path>SFX\Stinger2_F17FB28C.wem</Path>
				</File>
				<File Id="549514554" Language="SFX">
					<ShortName>Splat1.wav</ShortName>
					<Path>SFX\Splat1_794C6408.wem</Path>
				</File>
				<File Id="589612994" Language="SFX">
					<ShortName>IdleLoop.wav</ShortName>
					<Path>SFX\IdleLoop_F17FB28C.wem</Path>
				</File>
				<File Id="742496467" Language="SFX">
					<ShortName>Bite2.wav</ShortName>
					<Path>SFX\Bite2_1C9C67B2.wem</Path>
				</File>
				<File Id="744438766" Language="SFX">
					<ShortName>StingerPerc2.wav</ShortName>
					<Path>SFX\StingerPerc2_F17FB28C.wem</Path>
				</File>
				<File Id="806245137" Language="SFX">
					<ShortName>Splat2.wav</ShortName>
					<Path>SFX\Splat2_C55CDA9D.wem</Path>
				</File>
				<File Id="806302841" Language="SFX">
					<ShortName>StingerBite3.wav</ShortName>
					<Path>SFX\StingerBite3_F17FB28C.wem</Path>
				</File>
				<File Id="887608893" Language="SFX">
					<ShortName>StingerPerc7.wav</ShortName>
					<Path>SFX\StingerPerc7_F17FB28C.wem</Path>
				</File>
				<File Id="908220631" Language="SFX">
					<ShortName>BaseLoop2.wav</ShortName>
					<Path>SFX\BaseLoop2_F17FB28C.wem</Path>
				</File>
				<File Id="1045556741" Language="SFX">
					<ShortName>Bite1.wav</ShortName>
					<Path>SFX\Bite1_1C9C67B2.wem</Path>
				</File>
				<File Id="1066624553" Language="SFX">
					<ShortName>StingerPerc1.wav</ShortName>
					<Path>SFX\StingerPerc1_F17FB28C.wem</Path>
				</File>
				<File Id="1073477756" Language="SFX">
					<ShortName>Bite3.wav</ShortName>
					<Path>SFX\Bite3_1C9C67B2.wem</Path>
				</File>
			</IncludedMemoryFiles>
		</SoundBank>
	</SoundBanks>
</SoundBanksInfo>
